{
    "landmarks": [
        {
            "destinationID": "57b59706498e98e5bebecc78",
            "name": "Victoria Concert Hall - Home of the SSO",
            "latitude": 1.2884231627156355,
            "longitude": 103.8517798072363,
            "address": [
                "11 Empress Place (Connaught Drive)",
                "179558",
                "Singapore"
            ],
            "categoryID": "5032792091d4c4b30a586d5c"
        },
        {
            "destinationID": "4b05880ef964a520a8ae22e3",
            "name": "Victoria Theatre & Victoria Concert Hall",
            "latitude": 1.2883541544235495,
            "longitude": 103.85173122943438,
            "address": [
                "9 & 11 Empress Place (Connaught Drive)",
                "179558",
                "Singapore"
            ],
            "categoryID": "4bf58dd8d48988d12d941735"
        },
        {
            "destinationID": "4e7f3d04f5b97a346f1afe04",
            "name": "Singapore F1 GP: Padang Stage",
            "latitude": 1.2906966201285628,
            "longitude": 103.85329735080651,
            "address": [
                "Marina Bay Street Circuit (Zone 4)",
                "Singapore"
            ],
            "categoryID": "5032792091d4c4b30a586d5c"
        },
        {
            "destinationID": "56adbcd9498ef82f8911ca44",
            "name": "The Music Parlour",
            "latitude": 1.292012,
            "longitude": 103.850116,
            "address": [
                "#4-20 Peninsula Shopping Complex (3 Coleman Street)",
                "Singapore"
            ],
            "categoryID": "5032792091d4c4b30a586d5c"
        },
        {
            "destinationID": "4b058814f964a52090b022e3",
            "name": "Esplanade - Theatres On The Bay",
            "latitude": 1.2896881527433737,
            "longitude": 103.85512046310656,
            "address": [
                "1 Esplanade Dr.",
                "038981",
                "Singapore"
            ],
            "categoryID": "4bf58dd8d48988d1f2931735"
        },
        {
            "destinationID": "4e2bcfb7d164223a6986369d",
            "name": "ECH",
            "latitude": 1.289953,
            "longitude": 103.854116,
            "address": [
                "Singapore"
            ],
            "categoryID": "5032792091d4c4b30a586d5c"
        },
        {
            "destinationID": "50a784ace4b041c0652a1f03",
            "name": "Esplanade Concert Hall",
            "latitude": 1.2899135232745114,
            "longitude": 103.85498280184933,
            "address": [
                "Esplanade Theatres On The Bay (1 Esplanade Dr)",
                "Singapore"
            ],
            "categoryID": "5032792091d4c4b30a586d5c"
        },
        {
            "destinationID": "505eeec2e4b062a5a0589373",
            "name": "Noel Gallagher's Concert",
            "latitude": 1.2908,
            "longitude": 103.85437,
            "address": [
                "Singapore"
            ],
            "categoryID": "5032792091d4c4b30a586d5c"
        },
        {
            "destinationID": "4cce8d20c0378cfae0359448",
            "name": "Esplanade Recital Studio",
            "latitude": 1.2889965226009676,
            "longitude": 103.85579185019728,
            "address": [
                "Esplanade - Theatres On The Bay (1 Esplanade Drive)",
                "Singapore"
            ],
            "categoryID": "4bf58dd8d48988d1e5931735"
        },
        {
            "destinationID": "4c68dbb33bad2d7f2d82aeee",
            "name": "music@Recital Esplanade",
            "latitude": 1.28903,
            "longitude": 103.856047,
            "address": [
                "Singapore"
            ],
            "categoryID": "5032792091d4c4b30a586d5c"
        },
        {
            "destinationID": "4d7dcaa9dd4a6ea808015e25",
            "name": "Mosaic Music Station @ Esplanade",
            "latitude": 1.288787,
            "longitude": 103.856197,
            "address": [
                "Singapore"
            ],
            "categoryID": "5032792091d4c4b30a586d5c"
        },
        {
            "destinationID": "4ead29d029c2a9bb9781f417",
            "name": "Angra's Kiko Loureiro Asia Tour 2011",
            "latitude": 1.284853,
            "longitude": 103.850698,
            "address": [
                "Singapore"
            ],
            "categoryID": "5032792091d4c4b30a586d5c"
        },
        {
            "destinationID": "5131de4fe4b0ed893190db8b",
            "name": "Rachael Yamagata - Live!",
            "latitude": 1.289444,
            "longitude": 103.855236,
            "address": [
                "Esplanade Concert Hall",
                "Singapore"
            ],
            "categoryID": "5032792091d4c4b30a586d5c"
        },
        {
            "destinationID": "4f53260ce4b03be363b98807",
            "name": "Beautiful Sunday @ Esplanade",
            "latitude": 1.289994,
            "longitude": 103.856552,
            "address": [
                "Singapore"
            ],
            "categoryID": "5032792091d4c4b30a586d5c"
        },
        {
            "destinationID": "4fa8f3c6e4b00b5cf0c048f7",
            "name": "Follow Me On Instagram",
            "latitude": 1.293595,
            "longitude": 103.85214,
            "address": [
                "Singapore"
            ],
            "categoryID": "5032792091d4c4b30a586d5c"
        },
        {
            "destinationID": "4c75dbdeb474a1cd1fabbabf",
            "name": "Bay Room",
            "latitude": 1.2892715778808836,
            "longitude": 103.85589048061132,
            "address": [
                "1 Esplanade Drive",
                "Singapore"
            ],
            "categoryID": "4bf58dd8d48988d1f2931735"
        },
        {
            "destinationID": "4ee75674775ba356e071a7be",
            "name": "SSO Babies' Proms",
            "latitude": 1.2894543170028445,
            "longitude": 103.85514378547668,
            "address": [
                "Esplanade Concert Hall, 1 Esplanade Drive",
                "038981",
                "Singapore"
            ],
            "categoryID": "5032792091d4c4b30a586d5c"
        },
        {
            "destinationID": "50795b7fe4b0a4757dca17b0",
            "name": "Fort Canning Black Box Theater",
            "latitude": 1.294218,
            "longitude": 103.849455,
            "address": [
                "Singapore"
            ],
            "categoryID": "5032792091d4c4b30a586d5c"
        },
        {
            "destinationID": "4d0ea91926fba0930d25fe72",
            "name": "Esplanade Backstage",
            "latitude": 1.2895971019099208,
            "longitude": 103.8560433522522,
            "address": [
                "Singapore"
            ],
            "categoryID": "5032792091d4c4b30a586d5c"
        },
        {
            "destinationID": "4ce1337f41ed224b0ef1e83c",
            "name": "Esplanade RS Dressing Room",
            "latitude": 1.289459,
            "longitude": 103.856154,
            "address": [
                "Singapore"
            ],
            "categoryID": "5032792091d4c4b30a586d5c"
        },
        {
            "destinationID": "4eaab985dab40d132658f346",
            "name": "Kings And Queens Of Comedy 2 @ Esplanade",
            "latitude": 1.28888,
            "longitude": 103.855276,
            "address": [
                "Singapore"
            ],
            "categoryID": "5032792091d4c4b30a586d5c"
        },
        {
            "destinationID": "51e23604498e13baf8826470",
            "name": "City Harvest Church (Chinese Hall)",
            "latitude": 1.2936005222946543,
            "longitude": 103.85766833179386,
            "address": [
                "1 Raffles Boulevard (Suntec City Convention Center)",
                "039593",
                "Singapore"
            ],
            "categoryID": "5032792091d4c4b30a586d5c"
        },
        {
            "destinationID": "4e4e3b6ec65bb313ba740995",
            "name": "Simply Rahat Concert 19 August 2011",
            "latitude": 1.292784,
            "longitude": 103.858458,
            "address": [
                "Singapore"
            ],
            "categoryID": "5032792091d4c4b30a586d5c"
        },
        {
            "destinationID": "5441111a498e5781a7ab029b",
            "name": "Anugerah Planet Muzik 2014",
            "latitude": 1.29325532913208,
            "longitude": 103.8581771850586,
            "address": [
                "Singapore"
            ],
            "categoryID": "5032792091d4c4b30a586d5c"
        },
        {
            "destinationID": "527e2895498e91b0cd574a43",
            "name": "JJ / 林俊傑 Timeline World Tour",
            "latitude": 1.290273,
            "longitude": 103.858906,
            "address": [
                "Singapore Indoor Stadium",
                "Singapore"
            ],
            "categoryID": "5032792091d4c4b30a586d5c"
        },
        {
            "destinationID": "4fb62f52e4b0f8fec7e2f1f0",
            "name": "Sonu Nigam Rocks Singapore",
            "latitude": 1.293079,
            "longitude": 103.858114,
            "address": [
                "Singapore"
            ],
            "categoryID": "5032792091d4c4b30a586d5c"
        },
        {
            "destinationID": "4f4776abe4b05259390d0f3e",
            "name": "SLAM Concert",
            "latitude": 1.293252,
            "longitude": 103.857797,
            "address": [
                "Singapore"
            ],
            "categoryID": "5032792091d4c4b30a586d5c"
        },
        {
            "destinationID": "54818b30498e688230d42fbb",
            "name": "AFA2014 - I <3 Anisong",
            "latitude": 1.292705965156137,
            "longitude": 103.85821188328944,
            "address": [
                "Suntec Singapore Exhibition & Convention Center",
                "Singapore"
            ],
            "categoryID": "5032792091d4c4b30a586d5c"
        },
        {
            "destinationID": "50b9e210e4b04809bd2ed74b",
            "name": "2NE1 New Evolution g",
            "latitude": 1.2888121053332866,
            "longitude": 103.85881205725484,
            "address": [
                "Singapore"
            ],
            "categoryID": "5032792091d4c4b30a586d5c"
        },
        {
            "destinationID": "50456098e4b07d22d231c5e6",
            "name": "Hi5 Holiday!",
            "latitude": 1.284612,
            "longitude": 103.858825,
            "address": [
                "Grand Theatre (Marina Bay Sands)",
                "Singapore"
            ],
            "categoryID": "5032792091d4c4b30a586d5c"
        },
        {
            "destinationID": "4eb7d7062c5b53141b548966",
            "name": "Topone@bugis",
            "latitude": 1.298941,
            "longitude": 103.855857,
            "address": [
                "Singapore"
            ],
            "categoryID": "5032792091d4c4b30a586d5c"
        },
        {
            "destinationID": "4f4c8825e4b023d67558d0a5",
            "name": "Wong Fu Productions Live @ Suntec Rock Auditorium",
            "latitude": 1.294794454095231,
            "longitude": 103.86041442146903,
            "address": [
                "Singapore"
            ],
            "categoryID": "5032792091d4c4b30a586d5c"
        },
        {
            "destinationID": "51e5363e498e65d89c7a8040",
            "name": "The Phantom Of The Opera",
            "latitude": 1.2854210229029408,
            "longitude": 103.85951264104713,
            "address": [
                "MBS",
                "Singapore"
            ],
            "categoryID": "5032792091d4c4b30a586d5c"
        },
        {
            "destinationID": "5228b2e711d2170bedaaf4d2",
            "name": "Club Royal2",
            "latitude": 1.2848182120448681,
            "longitude": 103.84396702220937,
            "address": [
                "Singapore"
            ],
            "categoryID": "5032792091d4c4b30a586d5c"
        },
        {
            "destinationID": "50c06bbd8055b84272423bf8",
            "name": "Esplanade Theatre Studio",
            "latitude": 1.2896772808809123,
            "longitude": 103.85563891356041,
            "address": [
                "Esplanade - Theatres On The Bay (1 Esplanade Dr)",
                "038981",
                "Singapore"
            ],
            "categoryID": "4bf58dd8d48988d1f2931735"
        },
        {
            "destinationID": "4d3795267ebf721ef08268fb",
            "name": "The Sands Theatre",
            "latitude": 1.2852853016716066,
            "longitude": 103.86068620242959,
            "address": [
                "Marina Bay Sands (4 Bayfront Ave)",
                "018973",
                "Singapore"
            ],
            "categoryID": "4bf58dd8d48988d137941735"
        },
        {
            "destinationID": "4df2fb1bb0fb807158c0f5e3",
            "name": "Joyden Hall",
            "latitude": 1.2995152708207518,
            "longitude": 103.85424281584608,
            "address": [
                "#07-01, Bugis+ (201 Victoria St)",
                "188067",
                "Singapore"
            ],
            "categoryID": "4bf58dd8d48988d171941735"
        },
        {
            "destinationID": "4deb2a737d8b6c7a535350a4",
            "name": "SOTA Concert Hall",
            "latitude": 1.2989531832361736,
            "longitude": 103.84812604682637,
            "address": [
                "School of the Arts Singapore (1 Zubir Said Dr.)",
                "227968",
                "Singapore"
            ],
            "categoryID": "5032792091d4c4b30a586d5c"
        },
        {
            "destinationID": "4cc640a242d1b60c93752813",
            "name": "The Grand Theatre",
            "latitude": 1.2852797395330133,
            "longitude": 103.85971232316608,
            "address": [
                "Marina Bay Sands (4 Bayfront Ave)",
                "018973",
                "Singapore"
            ],
            "categoryID": "4bf58dd8d48988d137941735"
        }
    ]
}